{
  "project": "Markov's Maze",
  "source_policy": {
    "download_domain": "OpenGameArt only",
    "accepted_licenses": [
      "CC0",
      "CC-BY",
      "OGA-BY"
    ],
    "selected_license_set": [
      "CC0"
    ],
    "normalization_mode": "Stable filenames with extracted or copied runtime-ready WAV/OGG files. No loudness conversion was applied in this environment."
  },
  "items": [
    {
      "asset_id": "player_step",
      "category": "movement_sfx",
      "status": "sourced",
      "local_filename": "player_step_source.ogg",
      "raw_path": "assets/raw/audio/player_step_source.ogg",
      "processed_path": "assets/processed/audio/sfx/player_step.ogg",
      "source_type": "archive_member",
      "source_archive": "assets/raw/audio/kddDifferentSteps_0.zip",
      "archive_member": "stone01.ogg",
      "source_page_url": "https://opengameart.org/content/different-steps-on-wood-stone-leaves-gravel-and-mud",
      "direct_download_url": "https://opengameart.org/sites/default/files/%5Bkdd%5DDifferentSteps_0.zip",
      "asset_title": "Different steps on wood, stone, leaves, gravel and mud",
      "author": "TinyWorlds",
      "chosen_license": "CC0",
      "attribution_required": false,
      "exact_attribution_text": "",
      "notes": "Stone footstep chosen as the baseline maze movement cue."
    },
    {
      "asset_id": "player_move_intended",
      "category": "movement_sfx",
      "status": "sourced",
      "local_filename": "player_move_intended_source.wav",
      "raw_path": "assets/raw/audio/player_move_intended_source.wav",
      "processed_path": "assets/processed/audio/sfx/player_move_intended.wav",
      "source_type": "archive_member",
      "source_archive": "assets/raw/audio/tinysized.zip",
      "archive_member": "sfx-cc0/boots-leather-step-01.wav",
      "source_page_url": "https://opengameart.org/content/fantasy-sound-effects-tinysized-sfx",
      "direct_download_url": "https://opengameart.org/sites/default/files/tinysized.zip",
      "asset_title": "Fantasy Sound Effects (Tinysized SFX)",
      "author": "Vehicle",
      "chosen_license": "CC0",
      "attribution_required": false,
      "exact_attribution_text": "",
      "notes": "Leather step adds a slightly stronger committed move variant."
    },
    {
      "asset_id": "player_move_alternate",
      "category": "movement_sfx",
      "status": "sourced",
      "local_filename": "player_move_alternate_source.ogg",
      "raw_path": "assets/raw/audio/player_move_alternate_source.ogg",
      "processed_path": "assets/processed/audio/sfx/player_move_alternate.ogg",
      "source_type": "archive_member",
      "source_archive": "assets/raw/audio/kddDifferentSteps_0.zip",
      "archive_member": "gravel.ogg",
      "source_page_url": "https://opengameart.org/content/different-steps-on-wood-stone-leaves-gravel-and-mud",
      "direct_download_url": "https://opengameart.org/sites/default/files/%5Bkdd%5DDifferentSteps_0.zip",
      "asset_title": "Different steps on wood, stone, leaves, gravel and mud",
      "author": "TinyWorlds",
      "chosen_license": "CC0",
      "attribution_required": false,
      "exact_attribution_text": "",
      "notes": "Gravel variation distinguishes alternate movement outcomes without sounding like failure."
    },
    {
      "asset_id": "player_no_move",
      "category": "movement_sfx",
      "status": "sourced",
      "local_filename": "player_no_move_source.ogg",
      "raw_path": "assets/raw/audio/player_no_move_source.ogg",
      "processed_path": "assets/processed/audio/sfx/player_no_move.ogg",
      "source_type": "archive_member",
      "source_archive": "assets/raw/audio/kenney_interfaceSounds.zip",
      "archive_member": "Audio/tick_001.ogg",
      "source_page_url": "https://opengameart.org/content/interface-sounds",
      "direct_download_url": "https://opengameart.org/sites/default/files/kenney_interfaceSounds.zip",
      "asset_title": "Interface Sounds",
      "author": "Kenney",
      "chosen_license": "CC0",
      "attribution_required": false,
      "exact_attribution_text": "",
      "notes": "Soft tick used for the probabilistic stay-in-place result."
    },
    {
      "asset_id": "player_blocked_bump",
      "category": "hazard_sfx",
      "status": "sourced",
      "local_filename": "player_blocked_bump_source.ogg",
      "raw_path": "assets/raw/audio/player_blocked_bump_source.ogg",
      "processed_path": "assets/processed/audio/sfx/player_blocked_bump.ogg",
      "source_type": "archive_member",
      "source_archive": "assets/raw/audio/80-CC0-RPG-SFX_0.zip",
      "archive_member": "item_stone_02.ogg",
      "source_page_url": "https://opengameart.org/content/80-cc0-rpg-sfx",
      "direct_download_url": "https://opengameart.org/sites/default/files/80-CC0-RPG-SFX_0.zip",
      "asset_title": "80 CC0 RPG SFX",
      "author": "rubberduck",
      "chosen_license": "CC0",
      "attribution_required": false,
      "exact_attribution_text": "",
      "notes": "Stone impact variant selected for bumping into walls."
    },
    {
      "asset_id": "trap_trigger",
      "category": "hazard_sfx",
      "status": "sourced",
      "local_filename": "trap_trigger_source.ogg",
      "raw_path": "assets/raw/audio/trap_trigger_source.ogg",
      "processed_path": "assets/processed/audio/sfx/trap_trigger.ogg",
      "source_type": "archive_member",
      "source_archive": "assets/raw/audio/80-CC0-RPG-SFX_0.zip",
      "archive_member": "spell_01.ogg",
      "source_page_url": "https://opengameart.org/content/80-cc0-rpg-sfx",
      "direct_download_url": "https://opengameart.org/sites/default/files/80-CC0-RPG-SFX_0.zip",
      "asset_title": "80 CC0 RPG SFX",
      "author": "rubberduck",
      "chosen_license": "CC0",
      "attribution_required": false,
      "exact_attribution_text": "",
      "notes": "Magical spell snap used as the trap trigger cue."
    },
    {
      "asset_id": "lava_hiss_or_burst",
      "category": "hazard_sfx",
      "status": "sourced",
      "local_filename": "lava_hiss_or_burst_source.ogg",
      "raw_path": "assets/raw/audio/lava_hiss_or_burst_source.ogg",
      "processed_path": "assets/processed/audio/sfx/lava_hiss_or_burst.ogg",
      "source_type": "archive_member",
      "source_archive": "assets/raw/audio/80-CC0-RPG-SFX_0.zip",
      "archive_member": "spell_fire_04.ogg",
      "source_page_url": "https://opengameart.org/content/80-cc0-rpg-sfx",
      "direct_download_url": "https://opengameart.org/sites/default/files/80-CC0-RPG-SFX_0.zip",
      "asset_title": "80 CC0 RPG SFX",
      "author": "rubberduck",
      "chosen_license": "CC0",
      "attribution_required": false,
      "exact_attribution_text": "",
      "notes": "CC0 fire spell burst selected instead of retaining a CC-BY lava FLAC."
    },
    {
      "asset_id": "goal_activation",
      "category": "goal_sfx",
      "status": "sourced",
      "local_filename": "goal_activation_source.ogg",
      "raw_path": "assets/raw/audio/goal_activation_source.ogg",
      "processed_path": "assets/processed/audio/sfx/goal_activation.ogg",
      "source_type": "archive_member",
      "source_archive": "assets/raw/audio/80-CC0-RPG-SFX_0.zip",
      "archive_member": "spell_02.ogg",
      "source_page_url": "https://opengameart.org/content/80-cc0-rpg-sfx",
      "direct_download_url": "https://opengameart.org/sites/default/files/80-CC0-RPG-SFX_0.zip",
      "asset_title": "80 CC0 RPG SFX",
      "author": "rubberduck",
      "chosen_license": "CC0",
      "attribution_required": false,
      "exact_attribution_text": "",
      "notes": "Bright magic cue for the level goal activation."
    },
    {
      "asset_id": "level_complete",
      "category": "goal_sfx",
      "status": "sourced",
      "local_filename": "level_complete_source.ogg",
      "raw_path": "assets/raw/audio/level_complete_source.ogg",
      "processed_path": "assets/processed/audio/sfx/level_complete.ogg",
      "source_type": "archive_member",
      "source_archive": "assets/raw/audio/kenney_interfaceSounds.zip",
      "archive_member": "Audio/confirmation_004.ogg",
      "source_page_url": "https://opengameart.org/content/interface-sounds",
      "direct_download_url": "https://opengameart.org/sites/default/files/kenney_interfaceSounds.zip",
      "asset_title": "Interface Sounds",
      "author": "Kenney",
      "chosen_license": "CC0",
      "attribution_required": false,
      "exact_attribution_text": "",
      "notes": "Confirmation chime selected for end-of-level success."
    },
    {
      "asset_id": "defeat_sting",
      "category": "goal_sfx",
      "status": "sourced",
      "local_filename": "defeat_sting_source.ogg",
      "raw_path": "assets/raw/audio/defeat_sting_source.ogg",
      "processed_path": "assets/processed/audio/sfx/defeat_sting.ogg",
      "source_type": "archive_member",
      "source_archive": "assets/raw/audio/kenney_interfaceSounds.zip",
      "archive_member": "Audio/error_007.ogg",
      "source_page_url": "https://opengameart.org/content/interface-sounds",
      "direct_download_url": "https://opengameart.org/sites/default/files/kenney_interfaceSounds.zip",
      "asset_title": "Interface Sounds",
      "author": "Kenney",
      "chosen_license": "CC0",
      "attribution_required": false,
      "exact_attribution_text": "",
      "notes": "Short negative UI sting for defeat."
    },
    {
      "asset_id": "enemy_idle_cursed_hum",
      "category": "enemy_sfx",
      "status": "sourced",
      "local_filename": "enemy_idle_cursed_hum_source.ogg",
      "raw_path": "assets/raw/audio/enemy_idle_cursed_hum_source.ogg",
      "processed_path": "assets/processed/audio/sfx/enemy_idle_cursed_hum.ogg",
      "source_type": "direct_download",
      "source_page_url": "https://opengameart.org/content/ambient-horror",
      "direct_download_url": "https://opengameart.org/sites/default/files/ambient_horror_0.ogg",
      "asset_title": "Ambient horror",
      "author": "techiew",
      "chosen_license": "CC0",
      "attribution_required": false,
      "exact_attribution_text": "",
      "notes": "Loop-like ambient drone used as the cursed knight idle hum.",
      "downloaded_source_path": "assets/raw/audio/ambient_horror_0.ogg"
    },
    {
      "asset_id": "enemy_move_armor_scrape",
      "category": "enemy_sfx",
      "status": "sourced",
      "local_filename": "enemy_move_armor_scrape_source.wav",
      "raw_path": "assets/raw/audio/enemy_move_armor_scrape_source.wav",
      "processed_path": "assets/processed/audio/sfx/enemy_move_armor_scrape.wav",
      "source_type": "archive_member",
      "source_archive": "assets/raw/audio/tinysized.zip",
      "archive_member": "sfx-cc0/metal-knife-scrape-02.wav",
      "source_page_url": "https://opengameart.org/content/fantasy-sound-effects-tinysized-sfx",
      "direct_download_url": "https://opengameart.org/sites/default/files/tinysized.zip",
      "asset_title": "Fantasy Sound Effects (Tinysized SFX)",
      "author": "Vehicle",
      "chosen_license": "CC0",
      "attribution_required": false,
      "exact_attribution_text": "",
      "notes": "Metal scrape emphasizes the knight's armored movement."
    },
    {
      "asset_id": "enemy_spotted_alert",
      "category": "enemy_sfx",
      "status": "sourced",
      "local_filename": "enemy_spotted_alert_source.ogg",
      "raw_path": "assets/raw/audio/enemy_spotted_alert_source.ogg",
      "processed_path": "assets/processed/audio/sfx/enemy_spotted_alert.ogg",
      "source_type": "archive_member",
      "source_archive": "assets/raw/audio/kenney_interfaceSounds.zip",
      "archive_member": "Audio/question_003.ogg",
      "source_page_url": "https://opengameart.org/content/interface-sounds",
      "direct_download_url": "https://opengameart.org/sites/default/files/kenney_interfaceSounds.zip",
      "asset_title": "Interface Sounds",
      "author": "Kenney",
      "chosen_license": "CC0",
      "attribution_required": false,
      "exact_attribution_text": "",
      "notes": "Readable alert ping chosen for the line-of-sight detection moment."
    },
    {
      "asset_id": "ui_hover",
      "category": "ui_sfx",
      "status": "sourced",
      "local_filename": "ui_hover_source.ogg",
      "raw_path": "assets/raw/audio/ui_hover_source.ogg",
      "processed_path": "assets/processed/audio/sfx/ui_hover.ogg",
      "source_type": "archive_member",
      "source_archive": "assets/raw/audio/kenney_interfaceSounds.zip",
      "archive_member": "Audio/select_006.ogg",
      "source_page_url": "https://opengameart.org/content/interface-sounds",
      "direct_download_url": "https://opengameart.org/sites/default/files/kenney_interfaceSounds.zip",
      "asset_title": "Interface Sounds",
      "author": "Kenney",
      "chosen_license": "CC0",
      "attribution_required": false,
      "exact_attribution_text": "",
      "notes": "Menu hover cue."
    },
    {
      "asset_id": "ui_click",
      "category": "ui_sfx",
      "status": "sourced",
      "local_filename": "ui_click_source.ogg",
      "raw_path": "assets/raw/audio/ui_click_source.ogg",
      "processed_path": "assets/processed/audio/sfx/ui_click.ogg",
      "source_type": "archive_member",
      "source_archive": "assets/raw/audio/kenney_interfaceSounds.zip",
      "archive_member": "Audio/click_002.ogg",
      "source_page_url": "https://opengameart.org/content/interface-sounds",
      "direct_download_url": "https://opengameart.org/sites/default/files/kenney_interfaceSounds.zip",
      "asset_title": "Interface Sounds",
      "author": "Kenney",
      "chosen_license": "CC0",
      "attribution_required": false,
      "exact_attribution_text": "",
      "notes": "Menu confirm click."
    },
    {
      "asset_id": "restart_reset",
      "category": "ui_sfx",
      "status": "sourced",
      "local_filename": "restart_reset_source.ogg",
      "raw_path": "assets/raw/audio/restart_reset_source.ogg",
      "processed_path": "assets/processed/audio/sfx/restart_reset.ogg",
      "source_type": "archive_member",
      "source_archive": "assets/raw/audio/kenney_interfaceSounds.zip",
      "archive_member": "Audio/back_002.ogg",
      "source_page_url": "https://opengameart.org/content/interface-sounds",
      "direct_download_url": "https://opengameart.org/sites/default/files/kenney_interfaceSounds.zip",
      "asset_title": "Interface Sounds",
      "author": "Kenney",
      "chosen_license": "CC0",
      "attribution_required": false,
      "exact_attribution_text": "",
      "notes": "Restart/reset action cue."
    },
    {
      "asset_id": "menu_theme",
      "category": "music",
      "status": "sourced",
      "local_filename": "music_menu_theme_source.ogg",
      "raw_path": "assets/raw/audio/music_menu_theme_source.ogg",
      "processed_path": "assets/processed/audio/music/menu_theme.ogg",
      "source_type": "direct_download",
      "source_page_url": "https://opengameart.org/content/village-ruins",
      "direct_download_url": "https://opengameart.org/sites/default/files/Village%20Ruins%20-%20isaiah658.ogg",
      "asset_title": "Village Ruins",
      "author": "isaiah658",
      "chosen_license": "CC0",
      "attribution_required": false,
      "exact_attribution_text": "",
      "notes": "Selected for menu mood: wistful ruins theme.",
      "downloaded_source_path": "assets/raw/audio/music_menu_theme_source.ogg"
    },
    {
      "asset_id": "early_gameplay_theme",
      "category": "music",
      "status": "sourced",
      "local_filename": "music_early_gameplay_source.ogg",
      "raw_path": "assets/raw/audio/music_early_gameplay_source.ogg",
      "processed_path": "assets/processed/audio/music/early_gameplay_theme.ogg",
      "source_type": "direct_download",
      "source_page_url": "https://opengameart.org/content/dungeon-ambience",
      "direct_download_url": "https://opengameart.org/sites/default/files/dungeon002.ogg",
      "asset_title": "Dungeon Ambience",
      "author": "yd",
      "chosen_license": "CC0",
      "attribution_required": false,
      "exact_attribution_text": "",
      "notes": "Selected for early handcrafted maze levels.",
      "downloaded_source_path": "assets/raw/audio/music_early_gameplay_source.ogg"
    },
    {
      "asset_id": "late_gameplay_theme",
      "category": "music",
      "status": "sourced",
      "local_filename": "music_late_gameplay_source.ogg",
      "raw_path": "assets/raw/audio/music_late_gameplay_source.ogg",
      "processed_path": "assets/processed/audio/music/late_gameplay_theme.ogg",
      "source_type": "direct_download",
      "source_page_url": "https://opengameart.org/content/dark-cavern-ambient",
      "direct_download_url": "https://opengameart.org/sites/default/files/dark_cavern_ambient_002.ogg",
      "asset_title": "Dark Cavern Ambient",
      "author": "Paul Wortmann",
      "chosen_license": "CC0",
      "attribution_required": false,
      "exact_attribution_text": "",
      "notes": "Continuous loop selected for the later, tenser maze levels.",
      "downloaded_source_path": "assets/raw/audio/music_late_gameplay_source.ogg"
    }
  ],
  "summary": {
    "count": 19,
    "sfx_count": 16,
    "music_count": 3
  }
}
